dltk_ai/__init__.py
dltk_ai/core.py
dltk_ai/dataset_types.py
dltk_ai/image_preprocessor.py
dltk_ai/preprocessor.py
dltk_ai/visualization.py
dltk_ai/image_preprocessor_files/__init__.py
dltk_ai/image_preprocessor_files/opencv_preprocessor.py
dltk_ai/image_preprocessor_files/scikit_image_preprocessor.py
dltk_ai-1.1.9.dist-info/LICENSE
dltk_ai-1.1.9.dist-info/METADATA
dltk_ai-1.1.9.dist-info/WHEEL
dltk_ai-1.1.9.dist-info/top_level.txt
dltk_ai-1.1.9.dist-info/RECORD
