Metadata-Version: 2.1
Name: dltk-ai
Version: 1.1.9
Summary: Python Client for DLTK.
Home-page: https://github.com/dltk-ai/dltk-ai-sdk
Author: DLTK
Author-email: connect@qubitai.tech
License: UNKNOWN
Platform: UNKNOWN
Classifier: Programming Language :: Python :: 3
Classifier: License :: OSI Approved :: MIT License
Classifier: Operating System :: OS Independent
